pydlt_plus/__init__.py
pydlt_plus/dlt_filter.py
pydlt_plus/file.py
pydlt_plus/header.py
pydlt_plus/message.py
pydlt_plus/payload.py
pydlt_plus/setup.py
pydlt_plus-1.2.0.dist-info/METADATA
pydlt_plus-1.2.0.dist-info/WHEEL
pydlt_plus-1.2.0.dist-info/top_level.txt
pydlt_plus-1.2.0.dist-info/RECORD
